viturka/FM.als.py
viturka/FM_als.py
viturka/SGD.py
viturka/__init__.py
viturka/client.py
viturka/collaborative_filtering.py
viturka/fastfm.py
viturka/svd.py
viturka/utils.py
viturka-0.1.88.dist-info/LICENSE
viturka-0.1.88.dist-info/METADATA
viturka-0.1.88.dist-info/WHEEL
viturka-0.1.88.dist-info/top_level.txt
viturka-0.1.88.dist-info/RECORD
