Metadata-Version: 2.1
Name: viturka
Version: 0.1.88
Summary: A client library for federated learning platform.
License: MIT
Classifier: Programming Language :: Python :: 3
Classifier: License :: OSI Approved :: MIT License
Classifier: Operating System :: OS Independent
Requires-Python: >=3.6
License-File: LICENSE
Requires-Dist: numpy (==1.24.3)
Requires-Dist: pandas
Requires-Dist: fastFM
Requires-Dist: scikit-learn
Requires-Dist: scipy
Requires-Dist: seaborn
Requires-Dist: surprise
